infinite_tensor/__init__.py
infinite_tensor/infinite_tensor.py
infinite_tensor/tensor_window.py
infinite_tensor/utils.py
infinite_tensor/tilestore/__init__.py
infinite_tensor/tilestore/hdf5_tilestore.py
infinite_tensor-0.2.2.dist-info/licenses/LICENSE
infinite_tensor-0.2.2.dist-info/METADATA
infinite_tensor-0.2.2.dist-info/WHEEL
infinite_tensor-0.2.2.dist-info/top_level.txt
infinite_tensor-0.2.2.dist-info/RECORD
