Metadata-Version: 2.4
Name: infinite-tensor
Version: 0.2.2
Summary: A Python library for performing operations on tensors with infinite dimensions.
Author-email: Alexander Goslin <alexander.goslin@gmail.com>
License: MIT
Project-URL: Homepage, https://github.com/xandergos/infinite-tensor
Project-URL: Issues, https://github.com/xandergos/infinite-tensor/issues
Keywords: pytorch,tensor,infinite
Classifier: Programming Language :: Python :: 3
Classifier: License :: OSI Approved :: MIT License
Classifier: Operating System :: OS Independent
Requires-Python: >=3.9
License-File: LICENSE
Requires-Dist: numpy>=1.21.0
Requires-Dist: torch>=2.0.0
Provides-Extra: hdf5
Requires-Dist: h5py>=3.0.0; extra == "hdf5"
Dynamic: license-file
